{"Jo": {"name": "Jo", "phones": ["0971111111", "0974444444", "0975555555"], "email": null, "address": "lviv 18", "birthday": "10.12.1963", "note": null}, "Man": {"name": "Man", "phones": ["0505555555"], "email": "man@mail.com", "address": null, "birthday": "27.12.2000", "note": {"tag": "FRIEND", "message": "\u0441\u043f\u0440\u0430\u0432\u0436\u043d\u0456\u0439 \u0434\u0440\u0443\u0433 \u0404\u043d\u043e\u0442\u0430. \u0417\u0430\u0436\u0434\u0438 \u043c\u043e\u0436\u043d\u0430 \u043f\u043e\u043a\u043b\u0430\u0441\u0442\u0438\u0441\u044c."}}, "Jack": {"name": "Jack", "phones": ["0501111111"], "email": null, "address": "Vinnytsa, Main str., 20", "birthday": "30.12.1999", "note": {"tag": "MAIN", "message": "jack - \u043a\u0440\u0443\u0442\u0438\u0439 \u0454\u043d\u043e\u0442"}}, "Ho": {"name": "Ho", "phones": [], "email": null, "address": null, "birthday": "28.12.2010", "note": {"tag": "", "message": "\u044f\u043a\u0430\u0441\u044c \u043d\u043e\u0442\u0430\u0442\u043a\u0430 \u0434\u043e \u0434\u0438\u0432\u043d\u043e\u0433\u043e \u043a\u043e\u043d\u0442\u0430\u043a\u0442\u0430. \u0411\u0430\u0433\u0430\u0442\u043e \u043b\u0456\u0442\u0435\u0440."}}, "Jim": {"name": "Jim", "phones": ["0503333333"], "email": "jim@enote.com", "address": "green Forest", "birthday": "30.12.2010", "note": null}}